ranzen/__init__.py
ranzen/decorators.py
ranzen/hydra/__init__.py
ranzen/hydra/relay.py
ranzen/hydra/utils.py
ranzen/logging.py
ranzen/misc.py
ranzen/py.typed
ranzen/torch/__init__.py
ranzen/torch/data.py
ranzen/torch/loss.py
ranzen/torch/module.py
ranzen/torch/optimizers/__init__.py
ranzen/torch/optimizers/adafactor.py
ranzen/torch/optimizers/common.py
ranzen/torch/optimizers/lamb.py
ranzen/torch/optimizers/sam.py
ranzen/torch/sampling.py
ranzen/torch/schedulers.py
ranzen/torch/transforms/__init__.py
ranzen/torch/transforms/cutmix.py
ranzen/torch/transforms/mixup.py
ranzen/torch/transforms/utils.py
ranzen/torch/utils.py
ranzen/types.py
ranzen/wandb.py
ranzen-2.5.2.dist-info/LICENSE
ranzen-2.5.2.dist-info/METADATA
ranzen-2.5.2.dist-info/WHEEL
ranzen-2.5.2.dist-info/RECORD
