Metadata-Version: 2.1
Name: ranzen
Version: 2.5.2
Summary: A toolkit facilitating machine-learning experimentation.
Home-page: https://github.com/wearepal/ranzen
License: Apache-2.0
Keywords: typing,python
Author: PAL
Author-email: info@predictive-analytics-lab.com
Requires-Python: >=3.10,<3.13
Classifier: License :: OSI Approved :: Apache Software License
Classifier: Operating System :: OS Independent
Classifier: Programming Language :: Python :: 3
Classifier: Programming Language :: Python :: 3.10
Classifier: Programming Language :: Python :: 3.11
Classifier: Programming Language :: Python :: 3.12
Classifier: Typing :: Typed
Provides-Extra: all
Provides-Extra: hydra
Provides-Extra: logging
Provides-Extra: wandb
Requires-Dist: attrs (>=23.1.0,<24.0.0) ; extra == "hydra" or extra == "all"
Requires-Dist: backports.strenum (>=1.3.1,<2.0.0) ; python_version < "3.11"
Requires-Dist: hydra-core (>=1.3.0,<2.0.0) ; extra == "hydra" or extra == "all"
Requires-Dist: loguru (>=0.6.0,<0.7.0) ; extra == "logging" or extra == "all"
Requires-Dist: neoconfigen (>=2.4.2,<3.0.0) ; extra == "hydra" or extra == "all"
Requires-Dist: numpy (>=2.0,<3.0)
Requires-Dist: pandas (>=2.0.0,<3.0.0) ; extra == "wandb" or extra == "all"
Requires-Dist: typing-extensions (>=4.5.0)
Requires-Dist: wandb (>=0.15) ; extra == "wandb" or extra == "all"
Project-URL: Repository, https://github.com/wearepal/ranzen
